evolvishub_notification_adapter/__init__.py
evolvishub_notification_adapter/category.py
evolvishub_notification_adapter/config.py
evolvishub_notification_adapter/notification.py
evolvishub_notification_adapter/notification_db.py
evolvishub_notification_adapter/migrations/001_initial_schema.sql
evolvishub_notification_adapter/migrations/002_add_categories.sql
evolvishub_notification_adapter-0.1.4.dist-info/licenses/LICENSE
evolvishub_notification_adapter-0.1.4.dist-info/METADATA
evolvishub_notification_adapter-0.1.4.dist-info/WHEEL
evolvishub_notification_adapter-0.1.4.dist-info/top_level.txt
evolvishub_notification_adapter-0.1.4.dist-info/RECORD
