Metadata-Version: 2.4
Name: evolvishub-notification-adapter
Version: 0.1.4
Summary: A notification system adapter for Evolvishub
Home-page: https://github.com/evolvisai/evolvishub-notification-adapter
Author: Alban Maxhuni, PhD
Author-email: "Alban Maxhuni, PhD" <a.maxhuni@evolvis.ai>
License: MIT License
Project-URL: Homepage, https://github.com/evolvisai/evolvishub-notification-adapter
Project-URL: Repository, https://github.com/evolvisai/evolvishub-notification-adapter.git
Project-URL: Documentation, https://github.com/evolvisai/evolvishub-notification-adapter#readme
Classifier: Development Status :: 4 - Beta
Classifier: Intended Audience :: Developers
Classifier: License :: Other/Proprietary License
Classifier: Programming Language :: Python :: 3
Classifier: Programming Language :: Python :: 3.7
Classifier: Programming Language :: Python :: 3.8
Classifier: Programming Language :: Python :: 3.9
Classifier: Programming Language :: Python :: 3.10
Classifier: Programming Language :: Python :: 3.11
Classifier: Programming Language :: Python :: 3.12
Classifier: Operating System :: OS Independent
Requires-Python: >=3.7
License-File: LICENSE
Requires-Dist: pyyaml>=6.0
Requires-Dist: configparser>=5.0.0
Requires-Dist: python-dateutil>=2.8.2
Requires-Dist: aiosqlite>=0.19.0
Provides-Extra: dev
Requires-Dist: pytest>=7.0; extra == "dev"
Requires-Dist: pytest-cov>=4.0; extra == "dev"
Requires-Dist: black>=22.0; extra == "dev"
Requires-Dist: isort>=5.0; extra == "dev"
Requires-Dist: mypy>=0.900; extra == "dev"
Dynamic: author
Dynamic: home-page
Dynamic: license-file
Dynamic: requires-python
